{
  "url": "https://etsy.com",
  "status": "ok",
  "total_ms": 333.02967,
  "stages_ms": {
    "fetch": 0.137323,
    "css": 11.293172,
    "cascade": 52.559743000000005,
    "layout": 2.043085,
    "paint": 1.506364
  },
  "notes": "",
  "hotspot": "cascade",
  "failure_stage": null,
  "timeout_stage": null,
  "last_good_commit": "833aa788ed1a7102190a18ae8eae4a0af8876bc4",
  "last_regression_commit": "",
  "diagnostics": {
    "stats": {
      "timings": {
        "html_decode_ms": null,
        "dom_parse_ms": 0.137323,
        "css_inlining_ms": null,
        "css_parse_ms": 11.293172,
        "cascade_ms": 13.278807,
        "box_tree_ms": 39.280936,
        "layout_ms": 1.832351,
        "text_fallback_ms": 0.171894,
        "text_shape_ms": 0.210734,
        "paint_build_ms": 0.06503199999999999,
        "paint_optimize_ms": 0.0,
        "paint_rasterize_ms": 0.936911,
        "text_rasterize_ms": 0.504421,
        "encode_ms": null
      },
      "counts": {
        "dom_nodes": 13,
        "styled_nodes": 13,
        "box_nodes": 6,
        "fragments": 8,
        "shaped_runs": 2,
        "glyphs": 86,
        "color_glyph_rasters": 0,
        "fallback_cache_hits": 26,
        "fallback_cache_misses": 34,
        "last_resort_font_fallbacks": 0,
        "glyph_cache_hits": 0,
        "glyph_cache_misses": 0,
        "glyph_cache_evictions": 0,
        "glyph_cache_bytes": 0,
        "color_glyph_cache_hits": 0,
        "color_glyph_cache_misses": 0,
        "color_glyph_cache_evictions": 0,
        "color_glyph_cache_bytes": 0
      },
      "cascade": {
        "nodes": null,
        "rule_candidates": null,
        "rule_matches": null,
        "rule_candidates_pruned": null,
        "rule_candidates_by_id": null,
        "rule_candidates_by_class": null,
        "rule_candidates_by_tag": null,
        "rule_candidates_by_attr": null,
        "rule_candidates_universal": null,
        "selector_time_ms": null,
        "declaration_time_ms": null,
        "pseudo_time_ms": null,
        "has_evals": null,
        "has_cache_hits": null,
        "has_prunes": null,
        "has_bloom_prunes": null,
        "has_filter_prunes": null,
        "has_evaluated": null
      },
      "layout": {
        "intrinsic_lookups": 0,
        "intrinsic_hits": 0,
        "intrinsic_stores": 0,
        "block_intrinsic": 0,
        "flex_intrinsic": 0,
        "inline_intrinsic": 0,
        "table_cell_intrinsic_measurements": null,
        "table_cell_layouts": null,
        "layout_cache_lookups": 0,
        "layout_cache_hits": 0,
        "layout_cache_stores": 0,
        "layout_cache_evictions": 0,
        "layout_cache_clones": 0,
        "flex_cache_clones": 0,
        "taffy_nodes_built": 0,
        "taffy_nodes_reused": 0,
        "taffy_style_cache_hits": 0,
        "taffy_style_cache_misses": 0,
        "fragment_deep_clones": 0,
        "fragment_traversed": 0
      },
      "paint": {
        "display_items": 3,
        "optimized_items": null,
        "culled_items": null,
        "transparent_removed": null,
        "noop_removed": null,
        "merged_items": null,
        "gradient_ms": 0.0,
        "gradient_pixels": 0,
        "parallel_tasks": 0,
        "parallel_threads": 1,
        "parallel_ms": 0.0,
        "serial_ms": 1.001943,
        "filter_cache_hits": 0,
        "filter_cache_misses": 0,
        "blur_cache_hits": 0,
        "blur_cache_misses": 0,
        "blur_tiles": 0
      },
      "resources": {
        "fetch_counts": {},
        "resource_cache_fresh_hits": 0,
        "resource_cache_revalidated_hits": 0,
        "resource_cache_misses": 0,
        "image_cache_hits": 0,
        "image_cache_misses": 0,
        "image_decode_ms": 0.0
      }
    }
  }
}
