{
  "url": "https://www.netflix.com/",
  "status": "ok",
  "total_ms": 1771.097114,
  "stages_ms": {
    "fetch": 5.348643999999999,
    "css": 37.168318,
    "cascade": 174.36069399999997,
    "layout": 170.13597099999996,
    "paint": 964.270072
  },
  "notes": "",
  "hotspot": "paint",
  "failure_stage": "paint",
  "timeout_stage": null,
  "last_good_commit": "833aa788ed1a7102190a18ae8eae4a0af8876bc4",
  "last_regression_commit": "",
  "diagnostics": {
    "stats": {
      "timings": {
        "html_decode_ms": null,
        "dom_parse_ms": 5.348643999999999,
        "css_inlining_ms": null,
        "css_parse_ms": 37.168318,
        "cascade_ms": 140.328558,
        "box_tree_ms": 34.032135999999994,
        "layout_ms": 150.19052599999998,
        "text_fallback_ms": 40.63885499999998,
        "text_shape_ms": 19.945444999999985,
        "paint_build_ms": 823.545976,
        "paint_optimize_ms": 0.170014,
        "paint_rasterize_ms": 136.22215400000002,
        "text_rasterize_ms": 4.331927999999999,
        "encode_ms": null
      },
      "counts": {
        "dom_nodes": 1131,
        "styled_nodes": 1131,
        "box_nodes": 452,
        "fragments": 753,
        "shaped_runs": 1426,
        "glyphs": 36820,
        "color_glyph_rasters": 0,
        "fallback_cache_hits": 19652,
        "fallback_cache_misses": 18772,
        "last_resort_font_fallbacks": 0,
        "glyph_cache_hits": 277,
        "glyph_cache_misses": 61,
        "glyph_cache_evictions": 0,
        "glyph_cache_bytes": 16315,
        "color_glyph_cache_hits": 0,
        "color_glyph_cache_misses": 338,
        "color_glyph_cache_evictions": 0,
        "color_glyph_cache_bytes": 0
      },
      "cascade": {
        "nodes": null,
        "rule_candidates": null,
        "rule_matches": null,
        "rule_candidates_pruned": null,
        "rule_candidates_by_id": null,
        "rule_candidates_by_class": null,
        "rule_candidates_by_tag": null,
        "rule_candidates_by_attr": null,
        "rule_candidates_universal": null,
        "selector_time_ms": null,
        "declaration_time_ms": null,
        "pseudo_time_ms": null,
        "has_evals": null,
        "has_cache_hits": null,
        "has_prunes": null,
        "has_bloom_prunes": null,
        "has_filter_prunes": null,
        "has_evaluated": null
      },
      "layout": {
        "intrinsic_lookups": 3127,
        "intrinsic_hits": 2067,
        "intrinsic_stores": 1060,
        "block_intrinsic": 1387,
        "flex_intrinsic": 1740,
        "inline_intrinsic": 0,
        "table_cell_intrinsic_measurements": null,
        "table_cell_layouts": null,
        "layout_cache_lookups": 881,
        "layout_cache_hits": 154,
        "layout_cache_stores": 688,
        "layout_cache_evictions": 201,
        "layout_cache_clones": 154,
        "flex_cache_clones": 0,
        "taffy_nodes_built": 0,
        "taffy_nodes_reused": 0,
        "taffy_style_cache_hits": 0,
        "taffy_style_cache_misses": 0,
        "fragment_deep_clones": 0,
        "fragment_traversed": 0
      },
      "paint": {
        "display_items": 230,
        "optimized_items": 166,
        "culled_items": 0,
        "transparent_removed": 0,
        "noop_removed": 64,
        "merged_items": 0,
        "gradient_ms": 9.90221,
        "gradient_pixels": 378240,
        "parallel_tasks": 0,
        "parallel_threads": 1,
        "parallel_ms": 0.0,
        "serial_ms": 1779.970207,
        "filter_cache_hits": 0,
        "filter_cache_misses": 0,
        "blur_cache_hits": 0,
        "blur_cache_misses": 4,
        "blur_tiles": 0
      },
      "resources": {
        "fetch_counts": {
          "Stylesheet": 1,
          "Image": 18
        },
        "resource_cache_fresh_hits": 8,
        "resource_cache_revalidated_hits": 0,
        "resource_cache_misses": 5,
        "image_cache_hits": 8,
        "image_cache_misses": 18,
        "image_decode_ms": 2.067727
      }
    }
  }
}
